{
  "_meta": {
    "sources": [
      "loopback/common/models",
      "loopback/server/models",
      "../common/models",
      "./models"
    ],
    "mixins": [
      "loopback/common/mixins",
      "loopback/server/mixins",
      "../common/mixins",
      "./mixins"
    ]
  },
  "User": {
    "dataSource": "sharebindb"
  },
  "AccessToken": {
    "dataSource": "sharebindb",
    "public": false
  },
  "ACL": {
    "dataSource": "sharebindb",
    "public": false
  },
  "RoleMapping": {
    "dataSource": "sharebindb",
    "public": false,
    "options": {
      "strictObjectIDCoercion": true
    }
  },
  "Role": {
    "dataSource": "sharebindb",
    "public": false
  }
}
